jchannel/__init__.py
jchannel/channel.py
jchannel/frontend/__init__.py
jchannel/frontend/abstract.py
jchannel/frontend/ipython.py
jchannel/registry.py
jchannel/server.py
jchannel/types.py
jupyter_jchannel-0.3.9.dist-info/METADATA
jupyter_jchannel-0.3.9.dist-info/WHEEL
jupyter_jchannel-0.3.9.dist-info/entry_points.txt
jupyter_jchannel-0.3.9.dist-info/licenses/LICENSE
jupyter_jchannel-0.3.9.dist-info/RECORD
