Metadata-Version: 2.4
Name: jupyter-jchannel
Version: 0.3.9
Summary: Simple asynchronous RPC framework for Jupyter Notebooks. Facilitates calling JavaScript frontend code from Python kernel code and vice-versa.
License-File: LICENSE
Author: Marcelo Hashimoto
Author-email: marcelo.hashimoto@gmail.com
Requires-Python: >=3.12,<4.0
Classifier: Programming Language :: Python :: 3
Classifier: Programming Language :: Python :: 3.12
Classifier: Programming Language :: Python :: 3.13
Classifier: Programming Language :: Python :: 3.14
Requires-Dist: aiohttp (>=3.13.3,<4.0.0)
Project-URL: Repository, https://github.com/hashiprobr/jupyter-jchannel
